ranpicker/__init__.py
ranpicker/ranpicker.py
ranpicker-0.1.0.dist-info/licenses/LICENSE
ranpicker-0.1.0.dist-info/METADATA
ranpicker-0.1.0.dist-info/WHEEL
ranpicker-0.1.0.dist-info/top_level.txt
ranpicker-0.1.0.dist-info/RECORD
