Metadata-Version: 2.4
Name: ranpicker
Version: 0.1.0
Summary: Random picker for your random tasks
Author-email: gch131 <ggich@gmail.com>
License: MIT
Keywords: random,picker,generator,places,life,live
Classifier: Programming Language :: Python :: 3
Classifier: License :: OSI Approved :: MIT License
Classifier: Operating System :: OS Independent
Requires-Python: >=3.8
License-File: LICENSE
Dynamic: license-file
